discordmongo/__init__.py
discordmongo/exceptions.py
discordmongo/mongo.py
discordmongopy-0.3.0.dist-info/METADATA
discordmongopy-0.3.0.dist-info/WHEEL
discordmongopy-0.3.0.dist-info/entry_points.txt
discordmongopy-0.3.0.dist-info/top_level.txt
discordmongopy-0.3.0.dist-info/RECORD
