Metadata-Version: 2.1
Name: discordmongopy
Version: 0.3.0
Summary: A mongodb api wrapper to use in your discord bot
Home-page: UNKNOWN
Author: BongoPlayzYT
License: MIT
Platform: UNKNOWN
Classifier: License :: OSI Approved :: MIT License
Classifier: Programming Language :: Python :: 3
Classifier: Programming Language :: Python :: 3.7
Requires-Dist: pymongo
